scplot/__init__.py
scplot/plot.py
scplot-0.0.16.dist-info/LICENSE
scplot-0.0.16.dist-info/METADATA
scplot-0.0.16.dist-info/WHEEL
scplot-0.0.16.dist-info/top_level.txt
scplot-0.0.16.dist-info/RECORD
