Metadata-Version: 2.1
Name: scplot
Version: 0.0.16
Summary: Single cell plotting
Home-page: https://github.com/klarman-cell-observatory/scPlot
Author: Joshua Gould
Author-email: jgould@broadinstitute.org
License: BSD license
Keywords: plot
Platform: UNKNOWN
Classifier: License :: OSI Approved :: BSD License
Classifier: Intended Audience :: Developers
Classifier: Intended Audience :: Science/Research
Classifier: Natural Language :: English
Classifier: Operating System :: MacOS :: MacOS X
Classifier: Operating System :: Microsoft :: Windows
Classifier: Operating System :: POSIX :: Linux
Classifier: Programming Language :: Python :: 3
Classifier: Programming Language :: Python :: 3.5
Classifier: Programming Language :: Python :: 3.6
Classifier: Topic :: Scientific/Engineering :: Bio-Informatics
Classifier: Topic :: Scientific/Engineering :: Visualization
Requires-Dist: anndata
Requires-Dist: colorcet
Requires-Dist: holoviews
Requires-Dist: hvplot
Requires-Dist: natsort
Requires-Dist: numpy
Requires-Dist: pandas
Requires-Dist: scipy
